{"version":1,"resource":"file:///home/ene/.config/sway/run-dynamic-naming-script.sh","entries":[{"id":"JbgV.sh","timestamp":1695346459696},{"id":"8Ke0.sh","source":"renamed.source","timestamp":1695346544183},{"id":"iR8T.sh","timestamp":1695346906473},{"id":"r3cm.sh","timestamp":1695347001490},{"id":"4VRb.sh","timestamp":1695347158746},{"id":"x5iz.sh","timestamp":1695347259173},{"id":"nrcb.sh","timestamp":1695348208096},{"id":"Ynte.sh","timestamp":1695349250356},{"id":"GmKy.sh","timestamp":1695349388373},{"id":"fMIP.sh","timestamp":1695349437503},{"id":"d1Qm.sh","timestamp":1695349540466},{"id":"DQwc.sh","timestamp":1695349621033},{"id":"pvln.sh","timestamp":1695349645660},{"id":"ikuO.sh","timestamp":1695349691370},{"id":"hmnF.sh","timestamp":1695350046113},{"id":"pT1p.sh","timestamp":1695350201409},{"id":"1TqM.sh","timestamp":1695350321263},{"id":"SqLu.sh","timestamp":1695350391516},{"id":"j2iO.sh","timestamp":1695350463069},{"id":"qZu8.sh","timestamp":1695350599179},{"id":"jSjo.sh","timestamp":1695351986379},{"id":"6X6U.sh","timestamp":1695353259006},{"id":"G2au.sh","timestamp":1695354014439},{"id":"dhix.sh","timestamp":1695354357619},{"id":"HPPG.sh","timestamp":1695354742616},{"id":"Tl2S.sh","timestamp":1695354945396},{"id":"QEbI.sh","timestamp":1695355057232},{"id":"JVpF.sh","timestamp":1695355397436},{"id":"snUm.sh","timestamp":1695355623296},{"id":"Y4uL.sh","timestamp":1695355802632},{"id":"BWle.sh","timestamp":1695355846919},{"id":"YSDl.sh","timestamp":1695492467683},{"id":"PoNM.sh","timestamp":1695492880879},{"id":"MZ3Q.sh","timestamp":1695493069899},{"id":"rhNt.sh","timestamp":1695493137756},{"id":"mtFn.sh","source":"renamed.source","timestamp":1695495476057},{"id":"2Gk3.sh","source":"renamed.source","timestamp":1695495691746},{"id":"6p20.sh","timestamp":1695495751479},{"id":"P0FG.sh","timestamp":1695495862156},{"id":"y5qU.sh","timestamp":1695496728696},{"id":"dTpf.sh","timestamp":1695612372511},{"id":"DlDu.sh","source":"undoRedo.source","timestamp":1695612386678},{"id":"mmiQ.sh","timestamp":1695612512254},{"id":"HVo5.sh","timestamp":1695743546566},{"id":"0cOw.sh","timestamp":1695785334654},{"id":"3O8s.sh","source":"undoRedo.source","timestamp":1695785354287}]}