{"version":1,"resource":"file:///home/ene/.config/sway/switch-workspace-by-position.py","entries":[{"id":"qRHS.py","timestamp":1695496824662},{"id":"zJZv.py","timestamp":1695497476222},{"id":"SVkC.py","timestamp":1695497553912},{"id":"y3Ei.py","timestamp":1695497806522},{"id":"SLfK.py","timestamp":1695498626646},{"id":"P1Rm.py","timestamp":1695499163826},{"id":"339e.py","timestamp":1695499436892},{"id":"XpSi.py","timestamp":1695499579256},{"id":"iivP.py","timestamp":1695499815716},{"id":"KE6e.py","timestamp":1695608757764},{"id":"gdzR.py","timestamp":1695609161904},{"id":"wka3.py","source":"undoRedo.source","timestamp":1695609393544}]}